LICENCE
README.md
setup.py
Solver/__init__.py
Solver/api_console.py
api_console_solver.egg-info/PKG-INFO
api_console_solver.egg-info/SOURCES.txt
api_console_solver.egg-info/dependency_links.txt
api_console_solver.egg-info/requires.txt
api_console_solver.egg-info/top_level.txt