Metadata-Version: 2.1
Name: api-console-solver
Version: 0.0.21
Summary: Wrapper oficial da Plataforma Solver
Home-page: UNKNOWN
Author: Wesley Romualdo da Silva
Author-email: romualdo@solvedigital.com.br
License: MIT License
Keywords: console api
Platform: UNKNOWN
